CHANGELOG.txt
LICENCE.txt
MANIFEST.in
README.txt
setup.py
Construct_Code_py/Contruct_Code_py.py
Construct_Code_py/__init__.py
Construct_Code_py.egg-info/PKG-INFO
Construct_Code_py.egg-info/SOURCES.txt
Construct_Code_py.egg-info/dependency_links.txt
Construct_Code_py.egg-info/top_level.txt
Construct_Code_py/pytransform/__init__.py
Construct_Code_py/pytransform/__pycache__/__init__.cpython-37.pyc