Metadata-Version: 1.1
Name: Construct-Code-py
Version: 2.2.4
Summary: Generador de ID de Usuarios
Home-page: UNKNOWN
Author: Wilbert Sanchez
Author-email: wilbertenriquechable522@gmail.com
License: MIT
Keywords: IDs
Platform: UNKNOWN
Classifier: Development Status :: 5 - Production/Stable
Classifier: Intended Audience :: Education
Classifier: Operating System :: Microsoft :: Windows :: Windows 10
Classifier: License :: OSI Approved :: MIT License
Classifier: Programming Language :: Python :: 3
